{
  "$schema": "https://json-structure.org/meta/core/v0/#",
  "$id": "https://api-evangelist.github.io/amazon-application-migration-service/json-structure/application-migration-service-update-replication-configuration-template-request-structure.json",
  "title": "UpdateReplicationConfigurationTemplateRequest",
  "description": "Request to update a replication configuration template",
  "type": "record",
  "fields": {
    "replicationConfigurationTemplateID": {
      "type": "string",
      "description": "Template ID to update"
    },
    "stagingAreaSubnetId": {
      "type": "string",
      "description": "stagingAreaSubnetId"
    },
    "associateDefaultSecurityGroup": {
      "type": "boolean",
      "description": "associateDefaultSecurityGroup"
    },
    "replicationServerInstanceType": {
      "type": "string",
      "description": "replicationServerInstanceType"
    },
    "useLowBandwidthForReplication": {
      "type": "boolean",
      "description": "useLowBandwidthForReplication"
    },
    "dataPlaneRouting": {
      "type": "string",
      "description": "dataPlaneRouting"
    },
    "createPublicIP": {
      "type": "boolean",
      "description": "createPublicIP"
    }
  }
}